[
 {
  "id": "r1",
  "type": "rent",
  "address": "2115 E Ramsey Dr",
  "zip": "70808",
  "lat": 30.429043,
  "lon": -91.146854,
  "price": 2100,
  "petFees": "None listed",
  "beds": 2,
  "baths": 2,
  "size": 1850,
  "neighborhood": "Shea / Walnut Hills",
  "yearBuilt": "1950",
  "furnished": "no",
  "minLease": 12,
  "likes": "",
  "dislikes": "",
  "jamie": null,
  "keegan": 2,
  "link": "https://www.zillow.com/homedetails/2115-E-Ramsey-Dr-Baton-Rouge-LA-70808/66276675_zpid/",
  "status": "active"
 },
 {
  "id": "r2",
  "type": "rent",
  "address": "2437 Fiero St",
  "zip": "70808",
  "lat": 30.425011,
  "lon": -91.1619,
  "price": 2350,
  "petFees": "No pets allowed",
  "beds": 3,
  "baths": 3,
  "size": 2440,
  "neighborhood": "Hillsdale",
  "yearBuilt": "",
  "furnished": "",
  "minLease": 12,
  "likes": "",
  "dislikes": "",
  "jamie": null,
  "keegan": 1,
  "link": "https://www.zillow.com/homedetails/2437-Fiero-St-Baton-Rouge-LA-70808/119328538_zpid/",
  "status": "active"
 },
 {
  "id": "r3",
  "type": "rent",
  "address": "9003 Magnolia View Dr",
  "zip": "70810",
  "lat": 30.377,
  "lon": -91.115,
  "price": 2950,
  "petFees": "$200 non-refundable per pet deposit",
  "beds": 3,
  "baths": 2,
  "size": 1800,
  "neighborhood": "Garden District",
  "yearBuilt": "",
  "furnished": "fully",
  "minLease": 12,
  "likes": "",
  "dislikes": "don't want fully furnished for a full year",
  "jamie": null,
  "keegan": null,
  "link": "https://www.zillow.com/homedetails/9003-Magnolia-View-Dr-Baton-Rouge-LA-70810/2067541675_zpid/",
  "status": "active"
 },
 {
  "id": "r4",
  "type": "rent",
  "address": "415 Bedford Dr",
  "zip": "70806",
  "lat": 30.444959,
  "lon": -91.157492,
  "price": 2500,
  "petFees": "None listed",
  "beds": 3,
  "baths": 2,
  "size": 2000,
  "neighborhood": "Garden District (?)",
  "yearBuilt": "",
  "furnished": "fully",
  "minLease": null,
  "likes": "",
  "dislikes": "right above Government St; don't want fully furnished for a full year",
  "jamie": null,
  "keegan": null,
  "link": "https://www.redfin.com/LA/Baton-Rouge/415-Bedford-Dr-70806/home/85609683",
  "status": "active"
 },
 {
  "id": "r5",
  "type": "rent",
  "address": "417 Bedford Dr",
  "zip": "70806",
  "lat": 30.444939,
  "lon": -91.157492,
  "price": 2500,
  "petFees": "None listed",
  "beds": 3,
  "baths": 2,
  "size": 2000,
  "neighborhood": "Garden District (?)",
  "yearBuilt": "",
  "furnished": "fully",
  "minLease": null,
  "likes": "",
  "dislikes": "right above Government St; don't want fully furnished for a full year",
  "jamie": null,
  "keegan": null,
  "link": "https://www.redfin.com/LA/Baton-Rouge/417-Bedford-Dr-70806/home/185978878",
  "status": "active"
 },
 {
  "id": "r6",
  "type": "rent",
  "address": "9446 High Point Rd",
  "zip": "70810",
  "lat": 30.371114,
  "lon": -91.113354,
  "price": 2400,
  "petFees": "Pet-friendly",
  "beds": 3,
  "baths": null,
  "size": 2246,
  "neighborhood": "Wildwood",
  "yearBuilt": "",
  "furnished": "No",
  "minLease": null,
  "likes": "",
  "dislikes": "",
  "jamie": null,
  "keegan": null,
  "link": "https://www.zillow.com/homedetails/9446-High-Point-Rd-Baton-Rouge-LA-70810/66290884_zpid/",
  "status": "active"
 },
 {
  "id": "r7",
  "type": "rent",
  "address": "709 Staring Ln",
  "zip": "70810",
  "lat": 30.378812,
  "lon": -91.116969,
  "price": 2400,
  "petFees": "Dogs & cats allowed",
  "beds": 4,
  "baths": 2,
  "size": 2200,
  "neighborhood": "Highlands/Perkins (Staring Ln corridor)",
  "yearBuilt": "",
  "furnished": "No",
  "minLease": null,
  "likes": "Recently renovated; 1.2-acre lot; fireplace",
  "dislikes": "",
  "jamie": null,
  "keegan": null,
  "link": "https://www.zillow.com/homedetails/709-Staring-Ln-Baton-Rouge-LA-70810/66286645_zpid/",
  "status": "active"
 },
 {
  "id": "r8",
  "type": "rent",
  "address": "The Terraces at Perkins Rowe",
  "zip": "70810",
  "lat": 30.378031,
  "lon": -91.095543,
  "price": null,
  "petFees": "Pet-friendly",
  "beds": null,
  "baths": null,
  "size": null,
  "neighborhood": "Perkins Rowe / South BR",
  "yearBuilt": "2008",
  "furnished": "Some units",
  "minLease": 12,
  "likes": "",
  "dislikes": "Apartment community — Studio–4 bd, 606–2,171 sqft, ~$1,313–$3,488/mo",
  "jamie": null,
  "keegan": null,
  "link": "https://www.zillow.com/apartments/baton-rouge-la/the-terraces-at-perkins-rowe/CgLY46/",
  "status": "active"
 },
 {
  "id": "r9",
  "type": "rent",
  "address": "8808 Magnolia Leaf Ave",
  "zip": "70810",
  "lat": 30.378515,
  "lon": -91.116876,
  "price": null,
  "petFees": "",
  "beds": 3,
  "baths": 2,
  "size": 1752,
  "neighborhood": "Magnolia Trace (gated)",
  "yearBuilt": "2007",
  "furnished": "",
  "minLease": null,
  "likes": "nice bathtub",
  "dislikes": "",
  "jamie": null,
  "keegan": null,
  "link": "https://www.zillow.com/homedetails/8808-Magnolia-Leaf-Ave-Baton-Rouge-LA-70810/103858851_zpid/",
  "status": "off"
 },
 {
  "id": "r10",
  "type": "rent",
  "address": "4738 Woodlyn Dr",
  "zip": "70816",
  "lat": 30.408459,
  "lon": -91.038504,
  "price": 1900,
  "petFees": "",
  "beds": 3,
  "baths": 2,
  "size": 1750,
  "neighborhood": "Sherwood Oaks",
  "yearBuilt": "1985",
  "furnished": "",
  "minLease": null,
  "likes": "",
  "dislikes": "",
  "jamie": null,
  "keegan": null,
  "link": "https://www.zillow.com/homedetails/4738-Woodlyn-Dr-Baton-Rouge-LA-70816/66359973_zpid/",
  "status": "active"
 },
 {
  "id": "r11",
  "type": "rent",
  "address": "5416 Heron Nest Dr",
  "zip": "70816",
  "lat": 30.4282,
  "lon": -91.0193,
  "price": 2100,
  "petFees": "",
  "beds": 4,
  "baths": 3,
  "size": 1940,
  "neighborhood": "Parkview Oaks (South)",
  "yearBuilt": "",
  "furnished": "",
  "minLease": null,
  "likes": "",
  "dislikes": "",
  "jamie": null,
  "keegan": null,
  "link": "https://www.zillow.com/homedetails/5416-Heron-Nest-Dr-Baton-Rouge-LA-70816/2057143419_zpid/",
  "status": "active"
 },
 {
  "id": "r12",
  "type": "rent",
  "address": "6024 Woodlawn Park Ct",
  "zip": "70817",
  "lat": 30.397985,
  "lon": -91.018665,
  "price": 2100,
  "petFees": "",
  "beds": 4,
  "baths": 2,
  "size": 1975,
  "neighborhood": "Woodlawn Park",
  "yearBuilt": "1997",
  "furnished": "",
  "minLease": null,
  "likes": "All appliances incl. W/D",
  "dislikes": "",
  "jamie": null,
  "keegan": null,
  "link": "https://www.zillow.com/homedetails/6024-Woodlawn-Park-Ct-Baton-Rouge-LA-70817/66335004_zpid/",
  "status": "off"
 },
 {
  "id": "r13",
  "type": "rent",
  "address": "9314 Fox Run Ave",
  "zip": "70808",
  "lat": 30.365465,
  "lon": -91.122714,
  "price": null,
  "petFees": "",
  "beds": null,
  "baths": null,
  "size": 1773,
  "neighborhood": "South Burbank",
  "yearBuilt": "1981",
  "furnished": "",
  "minLease": null,
  "likes": "",
  "dislikes": "",
  "jamie": null,
  "keegan": null,
  "link": "https://www.zillow.com/homedetails/9314-Fox-Run-Ave-Baton-Rouge-LA-70808/66367221_zpid/",
  "status": "off"
 },
 {
  "id": "r14",
  "type": "rent",
  "address": "10177 Bonnet Cove Ave",
  "zip": "70810",
  "lat": 30.356855,
  "lon": -91.114277,
  "price": 1925,
  "petFees": "",
  "beds": 3,
  "baths": 3,
  "size": 2242,
  "neighborhood": "Bonnet Cove (townhomes)",
  "yearBuilt": "2008",
  "furnished": "",
  "minLease": null,
  "likes": "",
  "dislikes": "",
  "jamie": null,
  "keegan": null,
  "link": "https://www.zillow.com/homedetails/10177-Bonnet-Cove-Ave-Baton-Rouge-LA-70810/108609324_zpid/",
  "status": "off"
 },
 {
  "id": "r15",
  "type": "rent",
  "address": "633 Fall Creek Dr",
  "zip": "70810",
  "lat": 30.36123,
  "lon": -91.118092,
  "price": 1500,
  "petFees": "",
  "beds": 3,
  "baths": 2,
  "size": 1752,
  "neighborhood": "Summerwood",
  "yearBuilt": "",
  "furnished": "No",
  "minLease": null,
  "likes": "nice bathtub",
  "dislikes": "listing shows 2 ba but description says 2.5",
  "jamie": null,
  "keegan": null,
  "link": "https://www.zillow.com/homedetails/633-Fall-Creek-Dr-Baton-Rouge-LA-70810/70847864_zpid/",
  "status": "active"
 },
 {
  "id": "r16",
  "type": "rent",
  "address": "9412 Windward Rd",
  "zip": "70810",
  "lat": 30.369601,
  "lon": -91.114693,
  "price": 2000,
  "petFees": "Dogs & cats (deposit)",
  "beds": 4,
  "baths": 2,
  "size": 2200,
  "neighborhood": "East Highland",
  "yearBuilt": "",
  "furnished": "No",
  "minLease": "6 (or 12+)",
  "likes": "Lawn maintenance & many utilities included",
  "dislikes": "",
  "jamie": null,
  "keegan": null,
  "link": "https://www.zillow.com/homedetails/9412-Windward-Rd-Baton-Rouge-LA-70810/66297546_zpid/",
  "status": "active"
 },
 {
  "id": "r17",
  "type": "rent",
  "address": "4573 Charleston Villa Dr",
  "zip": "70817",
  "lat": 30.410339,
  "lon": -91.009528,
  "price": 2025,
  "petFees": "",
  "beds": 3,
  "baths": 2,
  "size": 1800,
  "neighborhood": "Charleston Villas",
  "yearBuilt": "2006",
  "furnished": "",
  "minLease": null,
  "likes": "",
  "dislikes": "",
  "jamie": null,
  "keegan": null,
  "link": "https://www.zillow.com/homedetails/4573-Charleston-Villa-Dr-Baton-Rouge-LA-70817/66808733_zpid/",
  "status": "active"
 },
 {
  "id": "r18",
  "type": "rent",
  "address": "620 Nelson Dr",
  "zip": "70808",
  "lat": 30.392817,
  "lon": -91.146962,
  "price": 2565,
  "petFees": "Pet-friendly",
  "beds": 3,
  "baths": 2,
  "size": 2000,
  "neighborhood": "Goodwood / Westdale area",
  "yearBuilt": "1960",
  "furnished": "No",
  "minLease": null,
  "likes": "",
  "dislikes": "price is a Zillow Rent Zestimate, not an asking rent",
  "jamie": null,
  "keegan": null,
  "link": "https://www.zillow.com/homedetails/620-Nelson-Dr-Baton-Rouge-LA-70808/66299495_zpid/",
  "status": "active"
 },
 {
  "id": "s1",
  "type": "sale",
  "address": "734 Caddo St",
  "zip": "70806",
  "lat": 30.44217,
  "lon": -91.137536,
  "price": 365,
  "beds": 4,
  "baths": 2,
  "size": 2404,
  "neighborhood": "Capital Heights",
  "yearBuilt": "1948",
  "likes": "",
  "dislikes": "no nice bathroom, asbestos",
  "jamie": null,
  "keegan": null,
  "link": "https://www.zillow.com/homedetails/734-Caddo-St-Baton-Rouge-LA-70806/66297410_zpid/",
  "status": "active"
 },
 {
  "id": "s2",
  "type": "sale",
  "address": "2103 Government St",
  "zip": "70806",
  "lat": 30.443929,
  "lon": -91.166762,
  "price": 425,
  "beds": 4,
  "baths": 2,
  "size": 2499,
  "neighborhood": "Garden District",
  "yearBuilt": "<1925",
  "likes": "",
  "dislikes": "no nice bathtub, no nice surrounding nature, 100+ years old",
  "jamie": null,
  "keegan": null,
  "link": "https://www.zillow.com/homedetails/2103-Government-St-Baton-Rouge-LA-70806/2057646869_zpid/",
  "status": "active"
 },
 {
  "id": "s3",
  "type": "sale",
  "address": "1525 S Eugene St",
  "zip": "70808",
  "lat": 30.434557,
  "lon": -91.159485,
  "price": 489,
  "beds": 3,
  "baths": 3,
  "size": 2236,
  "neighborhood": "Garden District",
  "yearBuilt": "1969",
  "likes": "",
  "dislikes": "",
  "jamie": null,
  "keegan": null,
  "link": "https://www.zillow.com/homedetails/1525-S-Eugene-St-Baton-Rouge-LA-70808/66277892_zpid/",
  "status": "unknown"
 },
 {
  "id": "s4",
  "type": "sale",
  "address": "750 Acadia St",
  "zip": "70806",
  "lat": 30.442059,
  "lon": -91.135516,
  "price": 535,
  "beds": 3,
  "baths": 3,
  "size": 2001,
  "neighborhood": "Capital Heights",
  "yearBuilt": "2025",
  "likes": "",
  "dislikes": "",
  "jamie": null,
  "keegan": null,
  "link": "https://www.zillow.com/homedetails/750-Acadia-St-Baton-Rouge-LA-70806/459629419_zpid/",
  "status": "active"
 },
 {
  "id": "s5",
  "type": "sale",
  "address": "541 Terry Dr",
  "zip": "70806",
  "lat": 30.443775,
  "lon": -91.152256,
  "price": 550,
  "beds": 4,
  "baths": 3,
  "size": 2886,
  "neighborhood": "Capital Heights",
  "yearBuilt": "1960",
  "likes": "beautiful bath",
  "dislikes": "",
  "jamie": null,
  "keegan": null,
  "link": "https://www.zillow.com/homedetails/541-Terry-Dr-Baton-Rouge-LA-70806/66275085_zpid/",
  "status": "active"
 },
 {
  "id": "s6",
  "type": "sale",
  "address": "740 Acadia St",
  "zip": "70806",
  "lat": 30.442169,
  "lon": -91.135519,
  "price": 575,
  "beds": 3,
  "baths": 3,
  "size": 2207,
  "neighborhood": "Capital Heights",
  "yearBuilt": "2025",
  "likes": "",
  "dislikes": "",
  "jamie": null,
  "keegan": null,
  "link": "https://www.zillow.com/homedetails/740-Acadia-St-Baton-Rouge-LA-70806/459629418_zpid/",
  "status": "active"
 },
 {
  "id": "s7",
  "type": "sale",
  "address": "2102 Sassy Ln",
  "zip": "70808",
  "lat": 30.418598,
  "lon": -91.150976,
  "price": 575,
  "beds": 3,
  "baths": 3,
  "size": 2529,
  "neighborhood": "Southdowns",
  "yearBuilt": "2002",
  "likes": "nice shower",
  "dislikes": "no nice tub shown",
  "jamie": null,
  "keegan": null,
  "link": "https://www.zillow.com/homedetails/2102-Sassy-Ln-Baton-Rouge-LA-70808/66383387_zpid/",
  "status": "active"
 },
 {
  "id": "s8",
  "type": "sale",
  "address": "2340 Government St",
  "zip": "70806",
  "lat": 30.443913,
  "lon": -91.162975,
  "price": 595,
  "beds": 4,
  "baths": 3,
  "size": 2628,
  "neighborhood": "Garden District",
  "yearBuilt": "1921",
  "likes": "",
  "dislikes": "no nice tub, old wood floors",
  "jamie": null,
  "keegan": null,
  "link": "https://www.zillow.com/homedetails/2340-Government-St-Baton-Rouge-LA-70806/66233850_zpid/",
  "status": "active"
 },
 {
  "id": "s9",
  "type": "sale",
  "address": "3650 Perkins Rd",
  "zip": "70808",
  "lat": 30.420714,
  "lon": -91.152251,
  "price": 605,
  "beds": 4,
  "baths": 3,
  "size": 2774,
  "neighborhood": "Southdowns",
  "yearBuilt": "1942",
  "likes": "",
  "dislikes": "no nice tub",
  "jamie": null,
  "keegan": null,
  "link": "https://www.zillow.com/homedetails/3650-Perkins-Rd-Baton-Rouge-LA-70808/66269726_zpid/",
  "status": "off"
 },
 {
  "id": "s10",
  "type": "sale",
  "address": "4468 Cypress St",
  "zip": "70808",
  "lat": 30.40908,
  "lon": -91.148653,
  "price": 625,
  "beds": 4,
  "baths": 3,
  "size": 2527,
  "neighborhood": "Southdowns",
  "yearBuilt": "1950",
  "likes": "jacuzzi",
  "dislikes": "",
  "jamie": null,
  "keegan": null,
  "link": "https://www.zillow.com/homedetails/4468-Cypress-St-Baton-Rouge-LA-70808/66269526_zpid/",
  "status": "active"
 },
 {
  "id": "s11",
  "type": "sale",
  "address": "2326 Terrace Ave",
  "zip": "70806",
  "lat": 30.436659,
  "lon": -91.163238,
  "price": 650,
  "beds": 4,
  "baths": 3,
  "size": 3259,
  "neighborhood": "Garden District",
  "yearBuilt": "1939",
  "likes": "",
  "dislikes": "bath nook not amazing, asbestos",
  "jamie": null,
  "keegan": null,
  "link": "https://www.zillow.com/homedetails/2326-Terrace-Ave-Baton-Rouge-LA-70806/66239341_zpid/",
  "status": "active"
 },
 {
  "id": "s12",
  "type": "sale",
  "address": "540 Drehr Ave",
  "zip": "70806",
  "lat": 30.443566,
  "lon": -91.163841,
  "price": 699,
  "beds": 4,
  "baths": 3.5,
  "size": 4452,
  "neighborhood": "Garden District",
  "yearBuilt": "1910",
  "likes": "",
  "dislikes": "no nice tub",
  "jamie": null,
  "keegan": null,
  "link": "https://www.zillow.com/homedetails/540-Drehr-Ave-Baton-Rouge-LA-70806/66237455_zpid/",
  "status": "active"
 },
 {
  "id": "s13",
  "type": "sale",
  "address": "2267 Cedardale Ave",
  "zip": "70808",
  "lat": 30.422878,
  "lon": -91.156875,
  "price": 732,
  "beds": 4,
  "baths": 4,
  "size": 3119,
  "neighborhood": "The Dales",
  "yearBuilt": "1986",
  "likes": "walking distance to Trader Joe's",
  "dislikes": "",
  "jamie": null,
  "keegan": null,
  "link": "https://www.zillow.com/homedetails/2267-Cedardale-Ave-Baton-Rouge-LA-70808/66266423_zpid/",
  "status": "active"
 },
 {
  "id": "s14",
  "type": "sale",
  "address": "4268 Arrowhead St",
  "zip": "70808",
  "lat": 30.414369,
  "lon": -91.148206,
  "price": 740,
  "beds": 4,
  "baths": 3.5,
  "size": 3067,
  "neighborhood": "Southdowns",
  "yearBuilt": "2009",
  "likes": "",
  "dislikes": "",
  "jamie": null,
  "keegan": null,
  "link": "https://www.redfin.com/LA/Baton-Rouge/4268-Arrowhead-St-70808/home/82920609",
  "status": "off"
 }
]